pfam2go/__init__.py
pfam2go-1.1.2.dist-info/LICENSE
pfam2go-1.1.2.dist-info/METADATA
pfam2go-1.1.2.dist-info/WHEEL
pfam2go-1.1.2.dist-info/top_level.txt
pfam2go-1.1.2.dist-info/RECORD
